LICENSE
MANIFEST.in
README.md
setup.py
PyQtMessageBar.egg-info/PKG-INFO
PyQtMessageBar.egg-info/SOURCES.txt
PyQtMessageBar.egg-info/dependency_links.txt
PyQtMessageBar.egg-info/requires.txt
PyQtMessageBar.egg-info/top_level.txt
docs/.nojekyll
docs/Makefile
docs/index.html
docs/make.bat
docs/stderr.log
docs/build/doctrees/api.doctree
docs/build/doctrees/environment.pickle
docs/build/doctrees/index.doctree
docs/build/doctrees/intro.doctree
docs/build/html/.buildinfo
docs/build/html/api.html
docs/build/html/genindex.html
docs/build/html/index.html
docs/build/html/intro.html
docs/build/html/objects.inv
docs/build/html/py-modindex.html
docs/build/html/search.html
docs/build/html/searchindex.js
docs/build/html/_images/affirmation_message.png
docs/build/html/_images/components.png
docs/build/html/_images/error_message.png
docs/build/html/_images/help_icons.png
docs/build/html/_images/inverted_smiley_18.png
docs/build/html/_images/inverted_smiley_24.png
docs/build/html/_images/testbed_at_startup.png
docs/build/html/_images/warning_message.png
docs/build/html/_modules/index.html
docs/build/html/_modules/pyqtmessagebar.html
docs/build/html/_modules/pyqtmessagebar/__init__.html
docs/build/html/_modules/pyqtmessagebar/waitqueuesignal.html
docs/build/html/_sources/api.rst.txt
docs/build/html/_sources/index.rst.txt
docs/build/html/_sources/intro.rst.txt
docs/build/html/_static/PyQtMessageBar_Components.pdn
docs/build/html/_static/PyQtMessageBar_Components_feathered.pdn
docs/build/html/_static/affirmation_message.png
docs/build/html/_static/basic.css
docs/build/html/_static/components.png
docs/build/html/_static/components_readme.png
docs/build/html/_static/doctools.js
docs/build/html/_static/documentation_options.js
docs/build/html/_static/error_message.png
docs/build/html/_static/file.png
docs/build/html/_static/help_icons.png
docs/build/html/_static/inverted_smiley.png
docs/build/html/_static/inverted_smiley_18.png
docs/build/html/_static/inverted_smiley_24.png
docs/build/html/_static/jquery-3.5.1.js
docs/build/html/_static/jquery.js
docs/build/html/_static/language_data.js
docs/build/html/_static/minus.png
docs/build/html/_static/plus.png
