Metadata-Version: 2.1
Name: PyQtMessageBar
Version: 0.3.2
Summary: Subclass of Qt's QStatusBar that adds a message buffer, wait queue, and user interaction.
Home-page: https://github.com/eruber/PyQtMessageBar
Author: E.R. Uber
Author-email: eruber@gmail.com
License: GPLv3
Download-URL: https://github.com/eruber/PyQtMessageBar/archive/v0.3.0.tar.gz
Platform: UNKNOWN
Classifier: Development Status :: 4 - Beta
Classifier: Intended Audience :: Developers
Classifier: License :: OSI Approved :: GNU General Public License v3 (GPLv3)
Classifier: Programming Language :: Python :: 3.7
Classifier: Programming Language :: Python :: 3.8
Requires: PyQt5
Requires-Python: >=3.7.1
